camlhmp/__init__.py
camlhmp/cli/__init__.py
camlhmp/cli/blast/__init__.py
camlhmp/cli/blast/alleles.py
camlhmp/cli/blast/regions.py
camlhmp/cli/blast/targets.py
camlhmp/cli/blast/thresholds.py
camlhmp/cli/camlhmp.py
camlhmp/cli/extract.py
camlhmp/engines/__init__.py
camlhmp/engines/blast.py
camlhmp/framework.py
camlhmp/parsers/__init__.py
camlhmp/parsers/blast.py
camlhmp/utils.py
camlhmp/visuals/__init__.py
camlhmp/visuals/framework.py
camlhmp-1.1.3.dist-info/METADATA
camlhmp-1.1.3.dist-info/WHEEL
camlhmp-1.1.3.dist-info/entry_points.txt
camlhmp-1.1.3.dist-info/licenses/LICENSE
camlhmp-1.1.3.dist-info/RECORD
