Metadata-Version: 2.4
Name: camlhmp
Version: 1.1.3
Summary: Classification through yAML Heuristic Mapping Protocol
License: MIT
License-File: LICENSE
Keywords: bioinformatics,bacteria,serotype,genotype
Author: Robert A. Petit III
Author-email: robbie.petit@gmail.com
Requires-Python: >=3.11,<4.0
Classifier: License :: OSI Approved :: MIT License
Classifier: Programming Language :: Python :: 3
Classifier: Programming Language :: Python :: 3.11
Classifier: Programming Language :: Python :: 3.12
Classifier: Programming Language :: Python :: 3.13
Classifier: Programming Language :: Python :: 3.14
Requires-Dist: biopython (>=1.83,<2.0)
Requires-Dist: executor (>=23.2,<24.0)
Requires-Dist: pyyaml (>=6.0.1,<7.0.0)
Requires-Dist: rich (>=13.7.1,<14.0.0)
Requires-Dist: rich-click (>=1.7.4,<2.0.0)
Project-URL: Homepage, https://github.com/rpetit3/camlhmp
Project-URL: Repository, https://github.com/rpetit3/camlhmp
